dock_cli/__init__.py
dock_cli/main.py
dock_cli/cli/__init__.py
dock_cli/cli/chart.py
dock_cli/cli/image.py
dock_cli/utils/__init__.py
dock_cli/utils/callback.py
dock_cli/utils/commands.py
dock_cli/utils/helpers.py
dock_cli/utils/schema.py
dock_cli/utils/utils.py
dock_cli-1.2.0.dist-info/LICENSE
dock_cli-1.2.0.dist-info/METADATA
dock_cli-1.2.0.dist-info/WHEEL
dock_cli-1.2.0.dist-info/entry_points.txt
dock_cli-1.2.0.dist-info/top_level.txt
dock_cli-1.2.0.dist-info/RECORD
