Metadata-Version: 2.1
Name: dock-cli
Version: 1.2.0
Summary: CLI for manage container applications
Author-email: Posen <posen2101024@gmail.com>
License: MIT License
Project-URL: Source, https://github.com/Posen2101024/dock
Requires-Python: >=3.8
License-File: LICENSE
Requires-Dist: click ~=8.1.7
Provides-Extra: test
Requires-Dist: pylint ; extra == 'test'
Requires-Dist: pytest ; extra == 'test'
Requires-Dist: pytest-cov ; extra == 'test'
Requires-Dist: pytest-mock ; extra == 'test'
Requires-Dist: pytest-pylint ; extra == 'test'
